{
  "project_info": {
    "project_number": "1089032382161",
    "project_id": "crypto-shift",
    "storage_bucket": "crypto-shift.firebasestorage.app"
  },
  "client": [
    {
      "client_info": {
        "mobilesdk_app_id": "1:1089032382161:android:35c9112b16339dd64d87f0",
        "android_client_info": {
          "package_name": "com.cryptoshift.crypto_shift_app"
        }
      },
      "oauth_client": [],
      "api_key": [
        {
          "current_key": "AIzaSyBwRHeN0IKlkk3M9UdJz-G_LqKWdL-XzOU"
        }
      ],
      "services": {
        "appinvite_service": {
          "other_platform_oauth_client": []
        }
      }
    }
  ],
  "configuration_version": "1"
}